<manifest alg="2" build="2018.1.0.386" opt="true" iceEnabled="true" iceMarkupVersion="2" iceEnabledOptions="link,responsive,cachebuster,textStyling" exportTarget="other" domain="binweil.github.io" resolutions="1x" timestamp="1566808183340">
  <folder name="css">
    <file name="site_global.css" crc="444006867"/>
    <file name="index.css" crc="4094083664" ref="index"/>
    <file name="project-videos.css" crc="3832374528" ref="project-videos"/>
    <file name="resumecv.css" crc="4047336647" ref="resumecv"/>
  </folder>
  <folder name="assets">
    <file name="resume_me_vehicle-.docx" crc="124329883" seo="true" mt="1566237544000"/>
  </folder>
  <folder name="scripts">
    <file name="jquery-1.8.3.min.js" crc="209076791" ref="index:resumecv:project-videos"/>
    <file name="museutils.js" crc="340535759" ref="index:resumecv:project-videos"/>
    <file name="whatinput.js" crc="86476730" ref="index:resumecv:project-videos"/>
    <file name="museconfig.js" crc="310584261" ref="index:resumecv:project-videos"/>
    <file name="jquery.musemenu.js" crc="510910590" ref="index"/>
    <file name="jquery.watch.js" crc="51536988" ref="index:resumecv:project-videos"/>
    <file name="html5shiv.js" crc="4241844378" ref="index:resumecv:project-videos"/>
    <file name="require.js" crc="7928878" ref="index:resumecv:project-videos"/>
  </folder>
  <folder name="images">
    <file name="pasted image 560x560.jpg" crc="446231419" seo="true" ref="index">
      <caption webpage="index" alt=""/>
    </file>
    <file name="pasted image 225x225.jpg" crc="7711740" seo="true" ref="index">
      <caption webpage="index" alt=""/>
    </file>
  </folder>
  <file name="index.html" crc="4250895316" seo="true" mt="1566807866939" redirect="true"/>
  <file name="resumecv.html" crc="4253845829" seo="true" mt="1566806697625" redirect="true"/>
  <file name="project-videos.html" crc="4094472121" seo="true" mt="1566807284850" redirect="true"/>
</manifest>